pgmini/__init__.py
pgmini/alias.py
pgmini/array.py
pgmini/case.py
pgmini/cast.py
pgmini/column.py
pgmini/delete.py
pgmini/distinct.py
pgmini/func.py
pgmini/insert.py
pgmini/literal.py
pgmini/marks.py
pgmini/operation.py
pgmini/operations.py
pgmini/operators.py
pgmini/order_by.py
pgmini/param.py
pgmini/raw.py
pgmini/select.py
pgmini/subquery.py
pgmini/table.py
pgmini/update.py
pgmini/utils.py
pgmini-0.1.14.dist-info/LICENSE
pgmini-0.1.14.dist-info/METADATA
pgmini-0.1.14.dist-info/WHEEL
pgmini-0.1.14.dist-info/RECORD
