Metadata-Version: 2.3
Name: pgmini
Version: 0.1.14
Summary: Build sql for PostgreSQL
License: MIT
Author: Vitalii Ponomar
Requires-Python: >=3.10
Classifier: License :: OSI Approved :: MIT License
Classifier: Programming Language :: Python :: 3
Classifier: Programming Language :: Python :: 3.10
Classifier: Programming Language :: Python :: 3.11
Classifier: Programming Language :: Python :: 3.12
Classifier: Programming Language :: Python :: 3.13
Requires-Dist: attrs (>=22.2.0)
Project-URL: Homepage, https://github.com/ponomar/pgmini
